demo/manage.py
demo/demo/__init__.py
demo/demo/asgi.py
demo/demo/settings.py
demo/demo/urls.py
demo/demo/wsgi.py
demo/demo/core/__init__.py
demo/demo/core/admin.py
demo/demo/core/apps.py
demo/demo/core/forms.py
demo/demo/core/models.py
demo/demo/core/tests.py
demo/demo/core/urls.py
demo/demo/core/views.py
demo/demo/core/wildewidgets.py
demo/demo/core/migrations/__init__.py
django_selectjs-0.3.7.dist-info/licenses/LICENSE.txt
docs/conf.py
selectjs/__init__.py
selectjs/apps.py
selectjs/urls.py
selectjs/views.py
selectjs/migrations/__init__.py
selectjs/static/css/model_many_to_many_search_select.css
selectjs/static/css/model_search_select.css
selectjs/static/js/model_many_to_many_search_select.js
selectjs/static/js/model_search_select.js
selectjs/templates/widgets/model_many_to_many_search_select.html
selectjs/templates/widgets/model_search_select.html
selectjs/widgets/__init__.py
selectjs/widgets/model_many_to_many_search_select.py
selectjs/widgets/model_search_select.py
django_selectjs-0.3.7.dist-info/METADATA
django_selectjs-0.3.7.dist-info/WHEEL
django_selectjs-0.3.7.dist-info/top_level.txt
django_selectjs-0.3.7.dist-info/RECORD
