Metadata-Version: 2.4
Name: django-selectjs
Version: 0.3.7
Summary: Django SelectJS - A replacement for Select2 that uses plain HTML and Javascript
Author-email: Caltech IMSS ADS <imss-ads-staff@caltech.edu>
Project-URL: Homepage, https://github.com/caltechads/django-selectjs
Project-URL: Repository, https://github.com/caltechads/django-selectjs
Keywords: select,widget,django
Classifier: Development Status :: 5 - Production/Stable
Classifier: Intended Audience :: Developers
Classifier: Operating System :: OS Independent
Classifier: Programming Language :: Python
Classifier: Programming Language :: Python :: 3.10
Classifier: Programming Language :: Python :: 3.11
Classifier: Programming Language :: Python :: 3.12
Classifier: Programming Language :: Python :: 3.13
Classifier: Framework :: Django
Classifier: Framework :: Django :: 4.2
Classifier: Framework :: Django :: 5
Classifier: Framework :: Django :: 5.1
Classifier: Framework :: Django :: 5.2
Classifier: Natural Language :: English
Classifier: Topic :: Database
Classifier: Topic :: Software Development :: Libraries
Classifier: Topic :: Software Development :: Libraries :: Python Modules
Requires-Python: >=3.10
License-File: LICENSE.txt
Requires-Dist: django>=5.2
Dynamic: license-file
